GPM_Playlist_Generator-1.2.1.data/scripts/gpm-playlistgen.py
gpmplgen/__init__.py
gpmplgen/__version__.py
gpmplgen/clientmock.py
gpmplgen/config.py
gpmplgen/gpmplgen.py
gpmplgen/db/__init__.py
gpmplgen/db/dbitem.py
gpmplgen/db/dbplaylist.py
gpmplgen/db/dbtrack.py
gpmplgen/db/librarydb.py
gpmplgen/gpm/__init__.py
gpmplgen/gpm/gpmitem.py
gpmplgen/gpm/playlist.py
gpmplgen/gpm/playlist_generator.py
GPM_Playlist_Generator-1.2.1.dist-info/LICENSE
GPM_Playlist_Generator-1.2.1.dist-info/METADATA
GPM_Playlist_Generator-1.2.1.dist-info/WHEEL
GPM_Playlist_Generator-1.2.1.dist-info/top_level.txt
GPM_Playlist_Generator-1.2.1.dist-info/RECORD
