Metadata-Version: 2.1
Name: GPM-Playlist-Generator
Version: 1.2.1
Summary: Google Play Music - Playlist Generator
Home-page: https://gitlab.com/hugoh/gpm-playlistgen
Author: Hugo Haas
Author-email: hugoh@hugoh.net
License: UNKNOWN
Keywords: google music,google play music,playlist,playlist generator
Platform: UNKNOWN
Classifier: Environment :: Console
Classifier: Programming Language :: Python
Classifier: Programming Language :: Python :: 2
Classifier: Programming Language :: Python :: 3
Classifier: Intended Audience :: End Users/Desktop
Classifier: Topic :: Multimedia :: Sound/Audio
Requires-Dist: gmusicapi
Requires-Dist: pyyaml
